cvisp/__init__.py
cvisp/utils.py
cvisp_demo-0.1.0.dist-info/LICENSE.txt
cvisp_demo-0.1.0.dist-info/METADATA
cvisp_demo-0.1.0.dist-info/WHEEL
cvisp_demo-0.1.0.dist-info/top_level.txt
cvisp_demo-0.1.0.dist-info/RECORD
