Metadata-Version: 2.1
Name: cvisp-demo
Version: 0.1.0
Summary: A small example package of demosaic-raw and cvisp, for our team
Home-page: https://github.com/HuiiJi
Author: Huii Ji
Author-email: 752413464@qq.com
Classifier: Programming Language :: Python :: 3
Classifier: License :: OSI Approved :: MIT License
Classifier: Operating System :: OS Independent
Requires-Python: >=3.9
License-File: LICENSE.txt
Requires-Dist: numpy
Requires-Dist: torch
Requires-Dist: opencv-python
Requires-Dist: tqdm
Requires-Dist: rawpy
